chrome_panel/__init__.py
chrome_panel/apps.py
chrome_panel/middleware.py
chrome_panel/panel.py
chrome_panel/settings.py
chrome_panel/utils.py
chrome_panel/views.py
chrome_panel-0.0.1.dist-info/DESCRIPTION.rst
chrome_panel-0.0.1.dist-info/METADATA
chrome_panel-0.0.1.dist-info/metadata.json
chrome_panel-0.0.1.dist-info/RECORD
chrome_panel-0.0.1.dist-info/top_level.txt
chrome_panel-0.0.1.dist-info/WHEEL
