Metadata-Version: 2.0
Name: chrome-panel
Version: 0.0.1
Summary: chrome debug panel
Home-page: https://github.com/bastianh
Author: Bastian Hoyer
Author-email: dafire@gmail.com
License: BSD License
Platform: UNKNOWN
Classifier: Development Status :: 1 - Planning
Classifier: Environment :: Web Environment
Classifier: Framework :: Django
Classifier: Intended Audience :: Developers
Classifier: License :: OSI Approved :: BSD License
Classifier: Operating System :: OS Independent
Classifier: Programming Language :: Python :: 3.3
Classifier: Topic :: Internet :: WWW/HTTP
Classifier: Topic :: Internet :: WWW/HTTP :: Dynamic Content
